{
  "period_id": "2026-01-19_15:15",
  "start_time": "2026-01-19T15:15:00",
  "end_time": "2026-01-19T15:30:01.824000",
  "summary": {
    "total_trades": 26,
    "wins": 15,
    "losses": 11,
    "pnl": -5.0,
    "win_rate": 57.7
  },
  "trades": [
    {
      "trade_id": 182,
      "asset_type": "PUT",
      "entry_price": 0.53,
      "exit_price": 0.59,
      "entry_time": "2026-01-19T15:15:01.011000",
      "exit_time": "2026-01-19T15:15:16.591000",
      "size": 100.0,
      "pnl": 6.0,
      "pnl_percent": 11.32,
      "exit_reason": "signal",
      "choppiness": 50.76,
      "volatility": 0.047
    },
    {
      "trade_id": 183,
      "asset_type": "CALL",
      "entry_price": 0.41,
      "exit_price": 0.48,
      "entry_time": "2026-01-19T15:15:16.591000",
      "exit_time": "2026-01-19T15:15:20.967000",
      "size": 100.0,
      "pnl": 7.0,
      "pnl_percent": 17.07,
      "exit_reason": "signal",
      "choppiness": 49.75,
      "volatility": 0.051
    },
    {
      "trade_id": 184,
      "asset_type": "PUT",
      "entry_price": 0.52,
      "exit_price": 0.5,
      "entry_time": "2026-01-19T15:15:20.967000",
      "exit_time": "2026-01-19T15:15:28.178000",
      "size": 100.0,
      "pnl": -2.0,
      "pnl_percent": -3.85,
      "exit_reason": "signal",
      "choppiness": 49.75,
      "volatility": 0.051
    },
    {
      "trade_id": 185,
      "asset_type": "CALL",
      "entry_price": 0.5,
      "exit_price": 0.44,
      "entry_time": "2026-01-19T15:15:28.178000",
      "exit_time": "2026-01-19T15:16:22.154000",
      "size": 100.0,
      "pnl": -6.0,
      "pnl_percent": -12.0,
      "exit_reason": "signal",
      "choppiness": 49.75,
      "volatility": 0.051
    },
    {
      "trade_id": 186,
      "asset_type": "PUT",
      "entry_price": 0.56,
      "exit_price": 0.65,
      "entry_time": "2026-01-19T15:16:22.154000",
      "exit_time": "2026-01-19T15:16:27.886000",
      "size": 100.0,
      "pnl": 9.0,
      "pnl_percent": 16.07,
      "exit_reason": "signal",
      "choppiness": 56.99,
      "volatility": 0.049
    },
    {
      "trade_id": 187,
      "asset_type": "CALL",
      "entry_price": 0.35,
      "exit_price": 0.35,
      "entry_time": "2026-01-19T15:16:27.886000",
      "exit_time": "2026-01-19T15:17:31.362000",
      "size": 100.0,
      "pnl": 0.0,
      "pnl_percent": 0.0,
      "exit_reason": "signal",
      "choppiness": 58.69,
      "volatility": 0.051
    },
    {
      "trade_id": 188,
      "asset_type": "PUT",
      "entry_price": 0.65,
      "exit_price": 0.72,
      "entry_time": "2026-01-19T15:17:31.362000",
      "exit_time": "2026-01-19T15:18:08.721000",
      "size": 100.0,
      "pnl": 7.0,
      "pnl_percent": 10.77,
      "exit_reason": "signal",
      "choppiness": 57.46,
      "volatility": 0.049
    },
    {
      "trade_id": 189,
      "asset_type": "CALL",
      "entry_price": 0.28,
      "exit_price": 0.34,
      "entry_time": "2026-01-19T15:18:08.721000",
      "exit_time": "2026-01-19T15:18:25.953000",
      "size": 100.0,
      "pnl": 6.0,
      "pnl_percent": 21.43,
      "exit_reason": "signal",
      "choppiness": 58.89,
      "volatility": 0.05
    },
    {
      "trade_id": 190,
      "asset_type": "PUT",
      "entry_price": 0.66,
      "exit_price": 0.67,
      "entry_time": "2026-01-19T15:18:25.953000",
      "exit_time": "2026-01-19T15:19:17.678000",
      "size": 100.0,
      "pnl": 1.0,
      "pnl_percent": 1.52,
      "exit_reason": "signal",
      "choppiness": 59.63,
      "volatility": 0.051
    },
    {
      "trade_id": 191,
      "asset_type": "CALL",
      "entry_price": 0.33,
      "exit_price": 0.37,
      "entry_time": "2026-01-19T15:19:17.678000",
      "exit_time": "2026-01-19T15:19:19.860000",
      "size": 100.0,
      "pnl": 4.0,
      "pnl_percent": 12.12,
      "exit_reason": "signal",
      "choppiness": 57.63,
      "volatility": 0.049
    },
    {
      "trade_id": 192,
      "asset_type": "PUT",
      "entry_price": 0.63,
      "exit_price": 0.55,
      "entry_time": "2026-01-19T15:19:19.860000",
      "exit_time": "2026-01-19T15:20:16.706000",
      "size": 100.0,
      "pnl": -8.0,
      "pnl_percent": -12.7,
      "exit_reason": "signal",
      "choppiness": 58.58,
      "volatility": 0.051
    },
    {
      "trade_id": 193,
      "asset_type": "CALL",
      "entry_price": 0.45,
      "exit_price": 0.49,
      "entry_time": "2026-01-19T15:20:16.706000",
      "exit_time": "2026-01-19T15:20:19.457000",
      "size": 100.0,
      "pnl": 4.0,
      "pnl_percent": 8.89,
      "exit_reason": "signal",
      "choppiness": 58.22,
      "volatility": 0.05
    },
    {
      "trade_id": 194,
      "asset_type": "PUT",
      "entry_price": 0.51,
      "exit_price": 0.54,
      "entry_time": "2026-01-19T15:20:19.457000",
      "exit_time": "2026-01-19T15:20:23.997000",
      "size": 100.0,
      "pnl": 3.0,
      "pnl_percent": 5.88,
      "exit_reason": "signal",
      "choppiness": 58.22,
      "volatility": 0.05
    },
    {
      "trade_id": 195,
      "asset_type": "CALL",
      "entry_price": 0.46,
      "exit_price": 0.25,
      "entry_time": "2026-01-19T15:20:23.997000",
      "exit_time": "2026-01-19T15:22:03.403000",
      "size": 100.0,
      "pnl": -21.0,
      "pnl_percent": -45.65,
      "exit_reason": "signal",
      "choppiness": 58.22,
      "volatility": 0.05
    },
    {
      "trade_id": 196,
      "asset_type": "PUT",
      "entry_price": 0.75,
      "exit_price": 0.71,
      "entry_time": "2026-01-19T15:22:03.403000",
      "exit_time": "2026-01-19T15:23:06.550000",
      "size": 100.0,
      "pnl": -4.0,
      "pnl_percent": -5.33,
      "exit_reason": "signal",
      "choppiness": 57.11,
      "volatility": 0.047
    },
    {
      "trade_id": 197,
      "asset_type": "CALL",
      "entry_price": 0.29,
      "exit_price": 0.4,
      "entry_time": "2026-01-19T15:23:06.550000",
      "exit_time": "2026-01-19T15:25:28.092000",
      "size": 100.0,
      "pnl": 11.0,
      "pnl_percent": 37.93,
      "exit_reason": "signal",
      "choppiness": 57.18,
      "volatility": 0.047
    },
    {
      "trade_id": 198,
      "asset_type": "PUT",
      "entry_price": 0.6,
      "exit_price": 0.6,
      "entry_time": "2026-01-19T15:25:28.092000",
      "exit_time": "2026-01-19T15:25:49.226000",
      "size": 100.0,
      "pnl": 0.0,
      "pnl_percent": 0.0,
      "exit_reason": "signal",
      "choppiness": 56.14,
      "volatility": 0.047
    },
    {
      "trade_id": 199,
      "asset_type": "CALL",
      "entry_price": 0.4,
      "exit_price": 0.46,
      "entry_time": "2026-01-19T15:25:49.226000",
      "exit_time": "2026-01-19T15:25:53.659000",
      "size": 100.0,
      "pnl": 6.0,
      "pnl_percent": 15.0,
      "exit_reason": "signal",
      "choppiness": 56.62,
      "volatility": 0.048
    },
    {
      "trade_id": 200,
      "asset_type": "PUT",
      "entry_price": 0.54,
      "exit_price": 0.54,
      "entry_time": "2026-01-19T15:25:53.659000",
      "exit_time": "2026-01-19T15:26:21.888000",
      "size": 100.0,
      "pnl": 0.0,
      "pnl_percent": 0.0,
      "exit_reason": "signal",
      "choppiness": 56.62,
      "volatility": 0.048
    },
    {
      "trade_id": 201,
      "asset_type": "CALL",
      "entry_price": 0.46,
      "exit_price": 0.5,
      "entry_time": "2026-01-19T15:26:21.888000",
      "exit_time": "2026-01-19T15:26:27.132000",
      "size": 100.0,
      "pnl": 4.0,
      "pnl_percent": 8.7,
      "exit_reason": "signal",
      "choppiness": 51.92,
      "volatility": 0.044
    },
    {
      "trade_id": 202,
      "asset_type": "PUT",
      "entry_price": 0.5,
      "exit_price": 0.35,
      "entry_time": "2026-01-19T15:26:27.132000",
      "exit_time": "2026-01-19T15:27:39.375000",
      "size": 100.0,
      "pnl": -15.0,
      "pnl_percent": -30.0,
      "exit_reason": "signal",
      "choppiness": 52.96,
      "volatility": 0.045
    },
    {
      "trade_id": 203,
      "asset_type": "CALL",
      "entry_price": 0.65,
      "exit_price": 0.76,
      "entry_time": "2026-01-19T15:27:39.375000",
      "exit_time": "2026-01-19T15:27:48.729000",
      "size": 100.0,
      "pnl": 11.0,
      "pnl_percent": 16.92,
      "exit_reason": "signal",
      "choppiness": 53.65,
      "volatility": 0.041
    },
    {
      "trade_id": 204,
      "asset_type": "PUT",
      "entry_price": 0.24,
      "exit_price": 0.33,
      "entry_time": "2026-01-19T15:27:48.729000",
      "exit_time": "2026-01-19T15:27:52.936000",
      "size": 100.0,
      "pnl": 9.0,
      "pnl_percent": 37.5,
      "exit_reason": "signal",
      "choppiness": 53.31,
      "volatility": 0.042
    },
    {
      "trade_id": 205,
      "asset_type": "CALL",
      "entry_price": 0.67,
      "exit_price": 0.64,
      "entry_time": "2026-01-19T15:27:52.936000",
      "exit_time": "2026-01-19T15:27:58.172000",
      "size": 100.0,
      "pnl": -3.0,
      "pnl_percent": -4.48,
      "exit_reason": "signal",
      "choppiness": 53.31,
      "volatility": 0.042
    },
    {
      "trade_id": 206,
      "asset_type": "PUT",
      "entry_price": 0.36,
      "exit_price": 0.51,
      "entry_time": "2026-01-19T15:27:58.172000",
      "exit_time": "2026-01-19T15:28:17.398000",
      "size": 100.0,
      "pnl": 15.0,
      "pnl_percent": 41.67,
      "exit_reason": "signal",
      "choppiness": 53.31,
      "volatility": 0.042
    },
    {
      "trade_id": 207,
      "asset_type": "CALL",
      "entry_price": 0.49,
      "exit_price": 0,
      "entry_time": "2026-01-19T15:28:17.398000",
      "exit_time": "2026-01-19T15:29:17.753000",
      "size": 100.0,
      "pnl": -49.0,
      "pnl_percent": -100.0,
      "exit_reason": "signal",
      "choppiness": 49.89,
      "volatility": 0.037
    }
  ]
}