{
  "period_id": "2026-01-19_03:15",
  "start_time": "2026-01-19T03:15:00",
  "end_time": "2026-01-19T03:30:01.833000",
  "summary": {
    "total_trades": 12,
    "wins": 5,
    "losses": 7,
    "pnl": 1.0,
    "win_rate": 41.7
  },
  "trades": [
    {
      "trade_id": 364,
      "asset_type": "PUT",
      "entry_price": 0.42,
      "exit_price": 0.42,
      "entry_time": "2026-01-19T03:16:14.548000",
      "exit_time": "2026-01-19T03:19:05.757000",
      "size": 100.0,
      "pnl": 0.0,
      "pnl_percent": 0.0,
      "exit_reason": "signal",
      "choppiness": 33.85,
      "volatility": 0.036
    },
    {
      "trade_id": 365,
      "asset_type": "CALL",
      "entry_price": 0.58,
      "exit_price": 0.58,
      "entry_time": "2026-01-19T03:19:05.757000",
      "exit_time": "2026-01-19T03:20:02.186000",
      "size": 100.0,
      "pnl": 0.0,
      "pnl_percent": 0.0,
      "exit_reason": "signal",
      "choppiness": 33.73,
      "volatility": 0.031
    },
    {
      "trade_id": 366,
      "asset_type": "PUT",
      "entry_price": 0.42,
      "exit_price": 0.49,
      "entry_time": "2026-01-19T03:20:02.186000",
      "exit_time": "2026-01-19T03:20:13.224000",
      "size": 100.0,
      "pnl": 7.0,
      "pnl_percent": 16.67,
      "exit_reason": "signal",
      "choppiness": 32.19,
      "volatility": 0.028
    },
    {
      "trade_id": 367,
      "asset_type": "CALL",
      "entry_price": 0.51,
      "exit_price": 0.52,
      "entry_time": "2026-01-19T03:20:13.224000",
      "exit_time": "2026-01-19T03:21:31.241000",
      "size": 100.0,
      "pnl": 1.0,
      "pnl_percent": 1.96,
      "exit_reason": "signal",
      "choppiness": 35.21,
      "volatility": 0.03
    },
    {
      "trade_id": 368,
      "asset_type": "PUT",
      "entry_price": 0.48,
      "exit_price": 0.59,
      "entry_time": "2026-01-19T03:21:31.241000",
      "exit_time": "2026-01-19T03:21:42.588000",
      "size": 100.0,
      "pnl": 11.0,
      "pnl_percent": 22.92,
      "exit_reason": "signal",
      "choppiness": 31.61,
      "volatility": 0.029
    },
    {
      "trade_id": 369,
      "asset_type": "CALL",
      "entry_price": 0.41,
      "exit_price": 0.36,
      "entry_time": "2026-01-19T03:21:42.588000",
      "exit_time": "2026-01-19T03:22:06.766000",
      "size": 100.0,
      "pnl": -5.0,
      "pnl_percent": -12.2,
      "exit_reason": "signal",
      "choppiness": 33.51,
      "volatility": 0.031
    },
    {
      "trade_id": 370,
      "asset_type": "PUT",
      "entry_price": 0.64,
      "exit_price": 0.72,
      "entry_time": "2026-01-19T03:22:06.766000",
      "exit_time": "2026-01-19T03:22:10.905000",
      "size": 100.0,
      "pnl": 8.0,
      "pnl_percent": 12.5,
      "exit_reason": "signal",
      "choppiness": 32.58,
      "volatility": 0.029
    },
    {
      "trade_id": 371,
      "asset_type": "CALL",
      "entry_price": 0.28,
      "exit_price": 0.1,
      "entry_time": "2026-01-19T03:22:10.905000",
      "exit_time": "2026-01-19T03:23:00.424000",
      "size": 100.0,
      "pnl": -18.0,
      "pnl_percent": -64.29,
      "exit_reason": "signal",
      "choppiness": 34.29,
      "volatility": 0.03
    },
    {
      "trade_id": 372,
      "asset_type": "PUT",
      "entry_price": 0.9,
      "exit_price": 0.93,
      "entry_time": "2026-01-19T03:23:00.424000",
      "exit_time": "2026-01-19T03:23:02.646000",
      "size": 100.0,
      "pnl": 3.0,
      "pnl_percent": 3.33,
      "exit_reason": "signal",
      "choppiness": 23.15,
      "volatility": 0.032
    },
    {
      "trade_id": 373,
      "asset_type": "CALL",
      "entry_price": 0.07,
      "exit_price": 0.06,
      "entry_time": "2026-01-19T03:23:02.646000",
      "exit_time": "2026-01-19T03:23:56.916000",
      "size": 100.0,
      "pnl": -1.0,
      "pnl_percent": -14.29,
      "exit_reason": "signal",
      "choppiness": 24.8,
      "volatility": 0.033
    },
    {
      "trade_id": 374,
      "asset_type": "PUT",
      "entry_price": 0.94,
      "exit_price": 0.94,
      "entry_time": "2026-01-19T03:23:56.916000",
      "exit_time": "2026-01-19T03:24:04.116000",
      "size": 100.0,
      "pnl": 0.0,
      "pnl_percent": 0.0,
      "exit_reason": "signal",
      "choppiness": 22.88,
      "volatility": 0.039
    },
    {
      "trade_id": 375,
      "asset_type": "CALL",
      "entry_price": 0.06,
      "exit_price": 0.01,
      "entry_time": "2026-01-19T03:24:04.116000",
      "exit_time": "2026-01-19T03:26:17.558000",
      "size": 100.0,
      "pnl": -5.0,
      "pnl_percent": -83.33,
      "exit_reason": "signal",
      "choppiness": 20.17,
      "volatility": 0.037
    }
  ]
}