{
  "period_id": "2026-01-19_05:30",
  "start_time": "2026-01-19T05:30:00",
  "end_time": "2026-01-19T05:45:01.488000",
  "summary": {
    "total_trades": 11,
    "wins": 7,
    "losses": 4,
    "pnl": -24.0,
    "win_rate": 63.6
  },
  "trades": [
    {
      "trade_id": 427,
      "asset_type": "CALL",
      "entry_price": 0.56,
      "exit_price": 0.67,
      "entry_time": "2026-01-19T05:30:01.351000",
      "exit_time": "2026-01-19T05:31:46.999000",
      "size": 100.0,
      "pnl": 11.0,
      "pnl_percent": 19.64,
      "exit_reason": "signal",
      "choppiness": 55.11,
      "volatility": 0.032
    },
    {
      "trade_id": 428,
      "asset_type": "PUT",
      "entry_price": 0.33,
      "exit_price": 0.37,
      "entry_time": "2026-01-19T05:31:46.999000",
      "exit_time": "2026-01-19T05:32:51.424000",
      "size": 100.0,
      "pnl": 4.0,
      "pnl_percent": 12.12,
      "exit_reason": "signal",
      "choppiness": 31.66,
      "volatility": 0.044
    },
    {
      "trade_id": 429,
      "asset_type": "CALL",
      "entry_price": 0.63,
      "exit_price": 0.34,
      "entry_time": "2026-01-19T05:32:51.424000",
      "exit_time": "2026-01-19T05:35:07.839000",
      "size": 100.0,
      "pnl": -29.0,
      "pnl_percent": -46.03,
      "exit_reason": "signal",
      "choppiness": 32.3,
      "volatility": 0.046
    },
    {
      "trade_id": 430,
      "asset_type": "PUT",
      "entry_price": 0.66,
      "exit_price": 0.78,
      "entry_time": "2026-01-19T05:35:07.839000",
      "exit_time": "2026-01-19T05:36:55.290000",
      "size": 100.0,
      "pnl": 12.0,
      "pnl_percent": 18.18,
      "exit_reason": "signal",
      "choppiness": 31.41,
      "volatility": 0.044
    },
    {
      "trade_id": 431,
      "asset_type": "CALL",
      "entry_price": 0.22,
      "exit_price": 0.32,
      "entry_time": "2026-01-19T05:36:55.290000",
      "exit_time": "2026-01-19T05:40:39.207000",
      "size": 100.0,
      "pnl": 10.0,
      "pnl_percent": 45.45,
      "exit_reason": "signal",
      "choppiness": 34.39,
      "volatility": 0.046
    },
    {
      "trade_id": 432,
      "asset_type": "PUT",
      "entry_price": 0.68,
      "exit_price": 0.54,
      "entry_time": "2026-01-19T05:40:39.207000",
      "exit_time": "2026-01-19T05:40:48.054000",
      "size": 100.0,
      "pnl": -14.0,
      "pnl_percent": -20.59,
      "exit_reason": "signal",
      "choppiness": 32.35,
      "volatility": 0.047
    },
    {
      "trade_id": 433,
      "asset_type": "CALL",
      "entry_price": 0.46,
      "exit_price": 0.72,
      "entry_time": "2026-01-19T05:40:48.054000",
      "exit_time": "2026-01-19T05:41:27.389000",
      "size": 100.0,
      "pnl": 26.0,
      "pnl_percent": 56.52,
      "exit_reason": "signal",
      "choppiness": 33.68,
      "volatility": 0.049
    },
    {
      "trade_id": 434,
      "asset_type": "PUT",
      "entry_price": 0.28,
      "exit_price": 0.29,
      "entry_time": "2026-01-19T05:41:27.389000",
      "exit_time": "2026-01-19T05:42:28.659000",
      "size": 100.0,
      "pnl": 1.0,
      "pnl_percent": 3.57,
      "exit_reason": "signal",
      "choppiness": 34.39,
      "volatility": 0.047
    },
    {
      "trade_id": 435,
      "asset_type": "CALL",
      "entry_price": 0.71,
      "exit_price": 0.37,
      "entry_time": "2026-01-19T05:42:28.659000",
      "exit_time": "2026-01-19T05:42:43.874000",
      "size": 100.0,
      "pnl": -34.0,
      "pnl_percent": -47.89,
      "exit_reason": "signal",
      "choppiness": 32.73,
      "volatility": 0.046
    },
    {
      "trade_id": 436,
      "asset_type": "PUT",
      "entry_price": 0.63,
      "exit_price": 0.75,
      "entry_time": "2026-01-19T05:42:43.874000",
      "exit_time": "2026-01-19T05:43:50.249000",
      "size": 100.0,
      "pnl": 12.0,
      "pnl_percent": 19.05,
      "exit_reason": "signal",
      "choppiness": 35.01,
      "volatility": 0.048
    },
    {
      "trade_id": 437,
      "asset_type": "CALL",
      "entry_price": 0.25,
      "exit_price": 0.02,
      "entry_time": "2026-01-19T05:43:50.249000",
      "exit_time": "2026-01-19T05:44:50.392000",
      "size": 100.0,
      "pnl": -23.0,
      "pnl_percent": -92.0,
      "exit_reason": "last_10s",
      "choppiness": 23.07,
      "volatility": 0.043
    }
  ]
}